[
  {
    "id": "a48d0ca6-98bd-4c00-9deb-c2dfe147103e",
    "name": "Dama Jóven - Collection 1",
    "description": "Dama Jóven - Collection 1",
    "positions": [
      "any",
      "any",
      "any",
      "any",
      "any",
      "any"
    ],
    "items": [
      [
        {
          "id": "881455037",
          "tag": "top",
          "views": [
            "881455038",
            "881455049",
            "881455055"
          ]
        }
      ],
      [
        {
          "id": "881099104",
          "tag": "bottom",
          "views": [
            "881368961",
            "881099115",
            "881454402",
            "881454409",
            "881454413",
            "881368950"
          ]
        }
      ],
      [
        {
          "id": "881433739",
          "tag": "top",
          "views": [
            "881433761",
            "881433740",
            "881433741",
            "881433742",
            "881433748",
            "881433751"
          ]
        }
      ],
      [
        {
          "id": "16483228",
          "tag": "accesorio",
          "views": [
            "16483228"
          ]
        }
      ],
      [
        {
          "id": "14201451",
          "tag": "accesorio",
          "views": [
            "14201451"
          ]
        }
      ],
      [
        {
          "id": "881431207",
          "tag": "accesorio",
          "views": [
            "881431209",
            "881431210"
          ]
        }
      ]
    ],
    "products": [
      "881455037",
      "881099104",
      "881433739",
      "16483228",
      "14201451",
      "881431207"
    ]
  },
  {
    "id": "fb3292db-62be-4c14-b3d4-3fd2297aa138",
    "name": "Dama Jóven - Collection 2",
    "description": "Dama Jóven - Collection 2",
    "positions": [
      "any",
      "any",
      "any",
      "any",
      "any",
      "any"
    ],
    "items": [
      [
        {
          "id": "881453433",
          "tag": "top",
          "views": [
            "881453434"
          ]
        }
      ],
      [
        {
          "id": "16623900",
          "tag": "calzado",
          "views": [
            "16623902"
          ]
        }
      ],
      [
        {
          "id": "16482649",
          "tag": "accesorio",
          "views": [
            "16482649"
          ]
        }
      ],
      [
        {
          "id": "881400268",
          "tag": "any",
          "views": [
            "881400269",
            "881400270",
            "881400271",
            "881400272"
          ]
        }
      ]
    ],
    "products": [
      "881453433",
      "16623900",
      "16482649",
      "881400268"
    ]
  },
  {
    "id": "1f4770f0-36dc-468a-b4c0-54a08da1dbe0",
    "name": "Juvenil Dama - Colección 1",
    "description": "Juvenil Dama - Colección 1",
    "positions": [
      "any",
      "any",
      "any",
      "any",
      "any",
      "any"
    ],
    "items": [
      [
        {
          "id": "881447322",
          "tag": "top",
          "views": [
            "881447323",
            "881447324",
            "881447325",
            "881447329"
          ]
        },
        {
          "id": "881431266",
          "tag": "accesorio",
          "views": [
            "881431267",
            "881431268",
            "881431269"
          ]
        }
      ],
      [
        {
          "id": "881103757",
          "tag": "bottom",
          "views": [
            "881103762",
            "881103758",
            "881103759"
          ]
        }
      ],
      [
        {
          "id": "881433232",
          "tag": "top",
          "views": [
            "881433233",
            "881433234",
            "881433237",
            "881433241",
            "881433244"
          ]
        }
      ],
      [
        {
          "id": "881397913",
          "tag": "calzado",
          "views": [
            "881397914"
          ]
        }
      ],
      [
        {
          "id": "16483228",
          "tag": "accesorio",
          "views": [
            "16483228"
          ]
        }
      ],
      [
        {
          "id": "14201451",
          "tag": "accesorio",
          "views": [
            "14201451"
          ]
        }
      ]
    ],
    "products": [
      "881447322",
      "881103757",
      "881433232",
      "881397913",
      "16483228",
      "14201451",
      "881431266"
    ]
  },
  {
    "id": "5e5cb9ce-6275-41da-9fca-050ef1955198",
    "name": "Juvenil Dama - Colección 2",
    "description": "Juvenil Dama - Colección 2",
    "positions": [
      "any",
      "any",
      "any",
      "any",
      "any",
      "any"
    ],
    "items": [
      [
        {
          "id": "881448878",
          "tag": "top",
          "views": [
            "881448880",
            "881448881"
          ]
        }
      ],
      [
        {
          "id": "881456413",
          "tag": "bottom",
          "views": [
            "881456416",
            "881456426",
            "881456415",
            "881456418",
            "881456420",
            "881456421",
            "881456424",
            "881456444"
          ]
        }
      ],
      [
        {
          "id": "16772330",
          "tag": "calzado",
          "views": [
            "16772331"
          ]
        }
      ],
      [
        {
          "id": "16482649",
          "tag": "accesorio",
          "views": [
            "16482649"
          ]
        }
      ],
      [
        {
          "id": "881430926",
          "tag": "accesorio",
          "views": [
            "881430927",
            "881430928",
            "881430930"
          ]
        }
      ],
      [
        {
          "id": "881388540",
          "tag": "any",
          "views": [
            "881388541",
            "881388544",
            "881388550"
          ]
        }
      ]
    ],
    "products": [
      "881448878",
      "881456413",
      "16772330",
      "16482649",
      "14184814",
      "881430926",
      "881388540"
    ]
  },
  {
    "id": "5362501b-8ff1-4080-9f73-df8e452cf8aa",
    "name": "Hombre Adulto - Colección 1",
    "description": "Hombre Adulto - Colección 1",
    "positions": [
      "top",
      "any",
      "any",
      "any",
      "any",
      "any"
    ],
    "items": [
      [
        {
          "id": "881471114",
          "tag": "top",
          "views": [
            "881471115",
            "881471116",
            "881471117",
            "881471120",
            "881471122",
            "881471123",
            "881471126"
          ]
        },
        {
          "id": "881354076",
          "tag": "top",
          "views": [
            "881354105",
            "881354082",
            "881354107",
            "881354116",
            "881354100",
            "881354090",
            "881354087",
            "881354088",
            "881354104",
            "881354097",
            "881354111",
            "881354108"
          ]
        }
      ],
      [
        {
          "id": "881350817",
          "tag": "bottom",
          "views": [
            "881350823",
            "881350827"
          ]
        },
        {
          "id": "881422589",
          "tag": "calzado",
          "views": [
            "881422590"
          ]
        }
      ],
      [
        {
          "id": "16045070",
          "tag": "accesorio",
          "views": [
            "16045070"
          ]
        }
      ],
      [
        {
          "id": "16256684",
          "tag": "accesorio",
          "views": [
            "16256684"
          ]
        }
      ],
      [
        {
          "id": "881358386",
          "tag": "any",
          "views": [
            "881358387",
            "881358388"
          ]
        }
      ],
      []
    ],
    "products": [
      "881471114",
      "881350817",
      "881354076",
      "881422589",
      "16045070",
      "16256684",
      "881358386"
    ]
  },
  {
    "id": "f41d3886-b397-419c-bd37-8609cc1172f3",
    "name": "Hombre Adulto - Colección 2",
    "description": "Hombre Adulto - Colección 2",
    "positions": [
      "any",
      "any",
      "any",
      "any",
      "any",
      "any"
    ],
    "items": [
      [
        {
          "id": "881422634",
          "tag": "calzado",
          "views": [
            "881422636"
          ]
        }
      ],
      [
        {
          "id": "16588121",
          "tag": "any",
          "views": [
            "16588121"
          ]
        }
      ]
    ],
    "products": [
      "881422634",
      "16588121"
    ]
  },
  {
    "id": "e243e153-d38d-4be7-b289-69018a4ec077",
    "name": "Hombre juvenil - Colección 1",
    "description": "Hombre juvenil - Colección 1",
    "positions": [
      "any",
      "any",
      "any",
      "any",
      "any",
      "any"
    ],
    "items": [
      [
        {
          "id": "881471114",
          "tag": "top",
          "views": [
            "881471115",
            "881471116",
            "881471117",
            "881471120",
            "881471122",
            "881471123",
            "881471126"
          ]
        },
        {
          "id": "881358386",
          "tag": "any",
          "views": [
            "881358387",
            "881358388"
          ]
        }
      ],
      [
        {
          "id": "881350817",
          "tag": "bottom",
          "views": [
            "881350823",
            "881350827"
          ]
        }
      ],
      [
        {
          "id": "881354076",
          "tag": "top",
          "views": [
            "881354105",
            "881354082",
            "881354107",
            "881354116",
            "881354100",
            "881354090",
            "881354087",
            "881354088",
            "881354104",
            "881354097",
            "881354111",
            "881354108"
          ]
        }
      ],
      [
        {
          "id": "881422589",
          "tag": "calzado",
          "views": [
            "881422590"
          ]
        }
      ],
      [
        {
          "id": "16045070",
          "tag": "accesorio",
          "views": [
            "16045070"
          ]
        }
      ],
      [
        {
          "id": "16256684",
          "tag": "accesorio",
          "views": [
            "16256684"
          ]
        }
      ]
    ],
    "products": [
      "881471114",
      "881350817",
      "881354076",
      "881422589",
      "16045070",
      "16256684",
      "881358386"
    ]
  },
  {
    "id": "2b19ebec-247d-4329-aa14-b22ea7047aa0",
    "name": "Hombre juvenil - Colección 2",
    "description": "Hombre juvenil - Colección 2",
    "positions": [
      "any",
      "any",
      "any",
      "any",
      "any",
      "any"
    ],
    "items": [
      [
        {
          "id": "881422634",
          "tag": "calzado",
          "views": [
            "881422636"
          ]
        }
      ],
      [
        {
          "id": "16588121",
          "tag": "any",
          "views": [
            "16588121"
          ]
        }
      ]
    ],
    "products": [
      "881422634",
      "16588121"
    ]
  },
  {
    "id": "4d66274e-a7ed-4fe3-ac1f-54bae902a054",
    "name": "Sala TV - Colección 1",
    "description": "Sala TV - Colección 1",
    "positions": [
      "tele",
      "any",
      "any",
      "any",
      "any",
      "any"
    ],
    "items": [
      [
        {
          "id": "16754143",
          "tag": "tele",
          "views": [
            "16754143"
          ]
        }
      ],
      [
        {
          "id": "881077421",
          "tag": "any",
          "views": [
            "881077421"
          ]
        }
      ],
      [
        {
          "id": "16289550",
          "tag": "any",
          "views": [
            "16289550"
          ]
        }
      ],
      [
        {
          "id": "13729634",
          "tag": "any",
          "views": [
            "13729634"
          ]
        }
      ],
      [
        {
          "id": "14952298",
          "tag": "any",
          "views": [
            "14952298"
          ]
        }
      ],
      [
        {
          "id": "881255708",
          "tag": "any",
          "views": [
            "881255708"
          ]
        }
      ]
    ],
    "products": [
      "16754143",
      "881077421",
      "16289550",
      "13729634",
      "14952298",
      "881255708"
    ]
  },
  {
    "id": "89e64d3f-2f1a-4bea-8635-b3aeb408ad1f",
    "name": "Smart home - Colección 1",
    "description": "Smart home - Colección 1",
    "positions": [
      "any",
      "any",
      "any",
      "any",
      "any",
      "any"
    ],
    "items": [
      [
        {
          "id": "16251944",
          "tag": "any",
          "views": [
            "16251944"
          ]
        },
        {
          "id": "16463443",
          "tag": "any",
          "views": [
            "16463443"
          ]
        }
      ],
      [
        {
          "id": "prod7920122",
          "tag": "any",
          "views": [
            "16256665",
            "16256664",
            "16256661",
            "16256663",
            "16256666",
            "16256662"
          ]
        }
      ],
      [
        {
          "id": "16436522",
          "tag": "any",
          "views": [
            "16436522"
          ]
        }
      ],
      [
        {
          "id": "15805951",
          "tag": "any",
          "views": [
            "15805951"
          ]
        }
      ],
      [
        {
          "id": "16544686",
          "tag": "any",
          "views": [
            "16544686"
          ]
        }
      ],
      [
        {
          "id": "16289550",
          "tag": "any",
          "views": [
            "16289550"
          ]
        }
      ]
    ],
    "products": [
      "16251944",
      "prod7920122",
      "16436522",
      "15805951",
      "16544686",
      "16289550",
      "16463443"
    ]
  }
]